[
    {
        "model": "proyecto_arriendos_crud.inmueble",
        "pk": 1,
        "fields": {
          "inmueble_nombre": "Casa de Campo",
          "descripcion": "Acogedora casa de campo",
          "m2_construidos": 150,
          "m2_terreno": 1000,
          "cantidad_estacionamientos": 2,
          "cantidad_habitaciones": 3,
          "cantidad_banios": 2,
          "direccion": 1,
          "tipo_inmueble": "casa",
          "precio_mensual_arriendo": 800000,
          "usuario_arrendador": 1,
          "disponibilidad": true
        }
    },
    {
        "model": "proyecto_arriendos_crud.inmueble",
        "pk": 2,
        "fields": {
          "inmueble_nombre": "Departamento Moderno",
          "descripcion": "Espacioso departamento con diseño moderno",
          "m2_construidos": 100,
          "m2_terreno": 0,
          "cantidad_estacionamientos": 1,
          "cantidad_habitaciones": 2,
          "cantidad_banios": 1,
          "direccion": 4,
          "tipo_inmueble": "departamento",
          "precio_mensual_arriendo": 600000,
          "usuario_arrendador": 10,
          "disponibilidad": true
        }
    },
    {
        "model": "proyecto_arriendos_crud.inmueble",
        "pk": 3,
        "fields": {
          "inmueble_nombre": "Cabaña de Playa",
          "descripcion": "Encantadora cabaña cerca del mar",
          "m2_construidos": 80,
          "m2_terreno": 500,
          "cantidad_estacionamientos": 0,
          "cantidad_habitaciones": 1,
          "cantidad_banios": 1,
          "direccion": 5,
          "tipo_inmueble": "parcela",
          "precio_mensual_arriendo": 400000,
          "usuario_arrendador": 9,
          "disponibilidad": true
        }
    },
    {
        "model": "proyecto_arriendos_crud.inmueble",
        "pk": 4,
        "fields": {
          "inmueble_nombre": "Oficina Ejecutiva",
          "descripcion": "Espacio ideal para oficinas ejecutivas",
          "m2_construidos": 120,
          "m2_terreno": 0,
          "cantidad_estacionamientos": 3,
          "cantidad_habitaciones": 4,
          "cantidad_banios": 2,
          "direccion": 8,
          "tipo_inmueble": "departamento",
          "precio_mensual_arriendo": 1000000,
          "usuario_arrendador": 5,
          "disponibilidad": true
        }
    },
    {
        "model": "proyecto_arriendos_crud.inmueble",
        "pk": 5,
        "fields": {
          "inmueble_nombre": "Loft Urbano",
          "descripcion": "Espacio abierto en el corazón de la ciudad",
          "m2_construidos": 90,
          "m2_terreno": 0,
          "cantidad_estacionamientos": 1,
          "cantidad_habitaciones": 1,
          "cantidad_banios": 1,
          "direccion": 9,
          "tipo_inmueble": "departamento",
          "precio_mensual_arriendo": 700000,
          "usuario_arrendador": 4,
          "disponibilidad": true
        }
    },
    {
        "model": "proyecto_arriendos_crud.inmueble",
        "pk": 6,
        "fields": {
          "inmueble_nombre": "Chalet en la Montaña",
          "descripcion": "Hermoso chalet con vistas panorámicas",
          "m2_construidos": 200,
          "m2_terreno": 800,
          "cantidad_estacionamientos": 2,
          "cantidad_habitaciones": 4,
          "cantidad_banios": 3,
          "direccion": 11,
          "tipo_inmueble": "casa",
          "precio_mensual_arriendo": 1200000,
          "usuario_arrendador": 1,
          "disponibilidad": true
        }
    },
    {
        "model": "proyecto_arriendos_crud.inmueble",
        "pk": 7,
        "fields": {
          "inmueble_nombre": "Preciosa Casa de un Piso",
          "descripcion": "Amplio patio y antejardín",
          "m2_construidos": 150,
          "m2_terreno": 0,
          "cantidad_estacionamientos": 2,
          "cantidad_habitaciones": 4,
          "cantidad_banios": 2,
          "direccion": 13,
          "tipo_inmueble": "casa",
          "precio_mensual_arriendo": 1300000,
          "usuario_arrendador": 10,
          "disponibilidad": true
        }
    },
    {
        "model": "proyecto_arriendos_crud.inmueble",
        "pk": 8,
        "fields": {
          "inmueble_nombre": "Penthouse con Vista al Mar",
          "descripcion": "Elegante penthouse con vistas al mar",
          "m2_construidos": 180,
          "m2_terreno": 0,
          "cantidad_estacionamientos": 2,
          "cantidad_habitaciones": 3,
          "cantidad_banios": 2,
          "direccion": 14,
          "tipo_inmueble": "departamento",
          "precio_mensual_arriendo": 1500000,
          "usuario_arrendador": 9,
          "disponibilidad": true
        }
    },
    {
        "model": "proyecto_arriendos_crud.inmueble",
        "pk": 9,
        "fields": {
          "inmueble_nombre": "Terreno Industrial",
          "descripcion": "Amplio terreno apto para industria",
          "m2_construidos": 0,
          "m2_terreno": 5000,
          "cantidad_estacionamientos": 0,
          "cantidad_habitaciones": 0,
          "cantidad_banios": 0,
          "direccion": 17,
          "tipo_inmueble": "parcela",
          "precio_mensual_arriendo": 500000,
          "usuario_arrendador": 5,
          "disponibilidad": true
        }
    },
    {
        "model": "proyecto_arriendos_crud.inmueble",
        "pk": 10,
        "fields": {
          "inmueble_nombre": "Bello Departamento",
          "descripcion": "Acogedor departamento de 2 ambientes",
          "m2_construidos": 30,
          "m2_terreno": 0,
          "cantidad_estacionamientos": 1,
          "cantidad_habitaciones": 1,
          "cantidad_banios": 1,
          "direccion": 19,
          "tipo_inmueble": "departamento",
          "precio_mensual_arriendo": 400000,
          "usuario_arrendador": 1,
          "disponibilidad": true
        }
    }    
]
